lm_agent/__init__.py
lm_agent/backend_utils/__init__.py
lm_agent/backend_utils/utils.py
lm_agent/config.py
lm_agent/constants.py
lm_agent/exceptions.py
lm_agent/logs.py
lm_agent/main.py
lm_agent/models.py
lm_agent/parsing/__init__.py
lm_agent/parsing/dsls.py
lm_agent/parsing/flexlm.py
lm_agent/parsing/lmx.py
lm_agent/parsing/lsdyna.py
lm_agent/parsing/olicense.py
lm_agent/parsing/rlm.py
lm_agent/scheduler.py
lm_agent/server_interfaces/__init__.py
lm_agent/server_interfaces/dsls.py
lm_agent/server_interfaces/flexlm.py
lm_agent/server_interfaces/license_server_interface.py
lm_agent/server_interfaces/lmx.py
lm_agent/server_interfaces/lsdyna.py
lm_agent/server_interfaces/olicense.py
lm_agent/server_interfaces/rlm.py
lm_agent/services/__init__.py
lm_agent/services/clean_jobs_and_bookings.py
lm_agent/services/license_report.py
lm_agent/services/reconciliation.py
lm_agent/utils.py
lm_agent/workload_managers/__init__.py
lm_agent/workload_managers/slurm/__init__.py
lm_agent/workload_managers/slurm/cmd_utils.py
lm_agent/workload_managers/slurm/common.py
lm_agent/workload_managers/slurm/reservations.py
lm_agent/workload_managers/slurm/slurmctld_epilog.py
lm_agent/workload_managers/slurm/slurmctld_prolog.py
license_manager_agent-4.5.0.dist-info/METADATA
license_manager_agent-4.5.0.dist-info/WHEEL
license_manager_agent-4.5.0.dist-info/entry_points.txt
license_manager_agent-4.5.0.dist-info/RECORD
