Metadata-Version: 2.4
Name: license-manager-agent
Version: 4.5.0
Summary: Provides an agent for interacting with license manager
License: MIT
Author: OmniVector Solutions
Author-email: info@omnivector.solutions
Requires-Python: >=3.12,<4.0
Classifier: License :: OSI Approved :: MIT License
Classifier: Programming Language :: Python :: 3
Classifier: Programming Language :: Python :: 3.12
Classifier: Programming Language :: Python :: 3.13
Classifier: Programming Language :: Python :: 3.14
Requires-Dist: PyJWT (>=2.10.0,<3.0.0)
Requires-Dist: apscheduler (==3.10.4)
Requires-Dist: httpx (>=0.28.1,<0.29.0)
Requires-Dist: py-buzz (>=7.3.0,<8.0.0)
Requires-Dist: pydantic (>=2.12,<3.0)
Requires-Dist: pydantic-settings (>=2.10.1,<3.0.0)
Requires-Dist: sentry-sdk (==2.38.0)
Project-URL: Documentation, https://omnivector-solutions.github.io/license-manager/
Project-URL: Repository, https://github.com/omnivector-solutions/license-manager
